{
    "version": "0.4",
    "title": "063 cat food__12",
    "type": "page",
    "content": [{"id":"3706a2c6","settings":{"gap":"wide","structure":"30","padding":{"unit":"px","top":"64","right":"0","bottom":"64","left":"0","isLinked":false},"padding_tablet":{"unit":"px","top":"50","right":"20","bottom":"50","left":"20","isLinked":false},"background_background":"classic","background_color":"#ff873f","background_overlay_background":"classic","background_overlay_image":{"url":"https:\/\/raw.githubusercontent.com\/muizzahabibi\/elementor-zahira\/main\/image\/landingpress.landingkit.co\/wp-content\/uploads\/2019\/07\/paww-pattern.png","id":9251},"background_overlay_position":"center center","background_overlay_repeat":"repeat","padding_mobile":{"unit":"em","top":"3","right":"2","bottom":"3","left":"2","isLinked":false},"content_position":"middle"},"elements":[{"id":"b61534a","settings":{"_column_size":33,"_inline_size":null,"margin_mobile":{"unit":"%","top":"0","right":"0","bottom":"10","left":"0","isLinked":false},"padding_mobile":{"unit":"px","top":"0","right":"0","bottom":"0","left":"0","isLinked":false},"padding":{"unit":"px","top":"0","right":"0","bottom":"0","left":"0","isLinked":false},"content_position":"center"},"elements":[{"id":"f5218ea","settings":{"image":{"url":"https:\/\/raw.githubusercontent.com\/muizzahabibi\/elementor-zahira\/main\/image\/landingpress.landingkit.co\/wp-content\/uploads\/2019\/07\/food-cat.png","id":9204},"align_tablet":"left","space_mobile":{"unit":"%","size":85},"align_mobile":"center","space_tablet":{"unit":"%","size":90},"fb_value":"0"},"elements":[],"isInner":false,"widgetType":"image","elType":"widget"}],"isInner":false,"elType":"column"},{"id":"372795ca","settings":{"_column_size":33,"_inline_size":null,"content_position":"center","padding_mobile":{"unit":"px","top":"0","right":"0","bottom":"0","left":"0","isLinked":false},"margin_mobile":{"unit":"%","top":"0","right":"0","bottom":"15","left":"0","isLinked":false}},"elements":[{"id":"29a935f2","settings":{"title":"Harga CATTY Food","header_size":"h3","align":"center","title_color":"#ffffff","typography_typography":"custom","typography_font_family":"Baloo","typography_font_size":{"unit":"px","size":30},"typography_font_size_tablet":{"unit":"px","size":26},"typography_font_size_mobile":{"unit":"px","size":20},"typography_line_height":{"unit":"em","size":1.5}},"elements":[],"isInner":false,"widgetType":"heading","elType":"widget"},{"id":"4d3a978b","settings":{"icon":"","title_text":"Rp 65.500","description_text":"Rp 49.950","title_size":"div","icon_space":{"unit":"px","size":0},"icon_size":{"unit":"px","size":6},"text_align_mobile":"center","title_bottom_space":{"unit":"px","size":0},"title_color":"#ffffff","title_typography_typography":"custom","title_typography_font_family":"Baloo","title_typography_font_size":{"unit":"px","size":16},"title_typography_font_weight":"100","_margin":{"unit":"%","top":"0","right":"0","bottom":"010","left":"0","isLinked":false},"content_vertical_alignment":"middle","title_typography_font_size_tablet":{"unit":"px","size":16},"title_typography_font_size_mobile":{"unit":"px","size":14},"title_typography_text_decoration":"line-through","description_color":"#ffffff","description_typography_typography":"custom","description_typography_font_family":"Baloo","description_typography_font_size":{"unit":"px","size":39},"description_typography_font_size_tablet":{"unit":"px","size":24},"description_typography_font_size_mobile":{"unit":"px","size":48},"_margin_mobile":{"unit":"px","top":"0","right":"0","bottom":"0","left":"0","isLinked":false},"_padding_mobile":{"unit":"px","top":"0","right":"0","bottom":"0","left":"0","isLinked":false}},"elements":[],"isInner":false,"widgetType":"icon-box","elType":"widget"},{"id":"19b5745b","settings":{"text":"Beli Sekarang","align":"center","size":"lg","background_color":"#ffffff","hover_color":"#ffffff","button_background_hover_color":"rgba(255,133,63,0)","hover_animation":"grow","button_text_color":"#ff843a","border_radius":{"unit":"px","top":"90","right":"90","bottom":"90","left":"90","isLinked":true},"align_mobile":"center","border_border":"solid","border_width":{"unit":"px","top":"1","right":"1","bottom":"1","left":"1","isLinked":true},"border_color":"#ffffff","fb_value":"0"},"elements":[],"isInner":false,"widgetType":"button","elType":"widget"}],"isInner":false,"elType":"column"},{"id":"34c9bedf","settings":{"_column_size":33,"_inline_size":null,"content_position":"center","padding_mobile":{"unit":"px","top":"0","right":"0","bottom":"0","left":"0","isLinked":false}},"elements":[{"id":"34c37ddd","settings":{"intro":"Beli sekarang sebelum kehabisan !!\u200b","month":"11","intro_color":"#ffffff","intro_typography_typography":"custom","intro_typography_font_weight":"800","year":"2020"},"elements":[],"isInner":false,"widgetType":"countdown_simple","elType":"widget"}],"isInner":false,"elType":"column"}],"isInner":false,"elType":"section"}],
    "page_settings": {
        "background_background": "classic",
        "background_color": "#ffffff",
        "template": "elementor_canvas"
    }
}